cloudmesh_pi_burn-4.3.29-py3.9-nspkg.pth
cloudmesh/burn/Imager.py
cloudmesh/burn/Iso.py
cloudmesh/burn/__init__.py
cloudmesh/burn/__version__.py
cloudmesh/burn/gui.py
cloudmesh/burn/hardware.py
cloudmesh/burn/image.py
cloudmesh/burn/network.py
cloudmesh/burn/sdcard.py
cloudmesh/burn/usb.py
cloudmesh/burn/util.py
cloudmesh/burn/burner/Burner.py
cloudmesh/burn/burner/BurnerABC.py
cloudmesh/burn/burner/RaspberryBurner.py
cloudmesh/burn/burner/__init__.py
cloudmesh/burn/burner/raspberryos.py
cloudmesh/burn/burner/ubuntu.py
cloudmesh/burn/command/__init__.py
cloudmesh/burn/command/burn.py
cloudmesh/burn/images/__init__.py
cloudmesh/burn/raspberryos/Locale.py
cloudmesh/burn/raspberryos/__init__.py
cloudmesh/burn/raspberryos/cmdline.py
cloudmesh/burn/raspberryos/passwd.py
cloudmesh/burn/raspberryos/runfirst.py
cloudmesh/burn/raspberryos/test.py
cloudmesh/burn/ubuntu/__init__.py
cloudmesh/burn/ubuntu/configure.py
cloudmesh/burn/ubuntu/networkdata.py
cloudmesh/burn/ubuntu/userdata.py
cloudmesh/burn/wifi/__init__.py
cloudmesh/burn/wifi/provider.py
cloudmesh/burn/wifi/raspberryos.py
cloudmesh/burn/wifi/ssid.py
cloudmesh/burn/wifi/ubuntu.py
cloudmesh_pi_burn-4.3.29.dist-info/LICENSE
cloudmesh_pi_burn-4.3.29.dist-info/METADATA
cloudmesh_pi_burn-4.3.29.dist-info/WHEEL
cloudmesh_pi_burn-4.3.29.dist-info/namespace_packages.txt
cloudmesh_pi_burn-4.3.29.dist-info/top_level.txt
cloudmesh_pi_burn-4.3.29.dist-info/RECORD
