Metadata-Version: 2.1
Name: cloudmesh-pi-burn
Version: 4.3.29
Summary: A command `cms burn` to burn many Raspberry PI SD Cards for buildiing PI Clusters with sshkeys and networking
Home-page: https://github.com/cloudmesh/cloudmesh-pi-burn
Author: Gregor von Laszewski
Author-email: laszewski@gmail.com
License: Apache 2.0
Platform: UNKNOWN
Classifier: Development Status :: 5 - Production/Stable
Classifier: Environment :: Web Environment
Classifier: Intended Audience :: Developers
Classifier: License :: OSI Approved :: BSD License
Classifier: Operating System :: OS Independent
Classifier: Programming Language :: Python
Classifier: Programming Language :: Python :: 3
Classifier: Programming Language :: Python :: 3.7
Classifier: Programming Language :: Python :: 3.8
Requires-Dist: cloudmesh-cmd5
Requires-Dist: cloudmesh-sys
Requires-Dist: cloudmesh-inventory
Requires-Dist: cloudmesh-configuration
Requires-Dist: cloudmesh-common
Requires-Dist: humanize
Requires-Dist: wget
Requires-Dist: python-hostlist
Requires-Dist: docopt
Requires-Dist: prompter
Requires-Dist: pyyaml
Requires-Dist: oyaml
Requires-Dist: requests
Requires-Dist: pyusb
Requires-Dist: tqdm
Requires-Dist: PySimpleGUI
Requires-Dist: passlib
